AUTHORS.rst
CHANGELOG.rst
CONTRIBUTING.rst
MANIFEST.in
README.rst
requirements.txt
setup.py
docs/Makefile
docs/authors.rst
docs/changelog.rst
docs/conf.py
docs/contributing.rst
docs/frontier.IO.rst
docs/frontier.rst
docs/index.rst
docs/installation.rst
docs/make.bat
docs/modules.rst
docs/readme.rst
docs/usage.rst
frontier/__init__.py
frontier/frontier.py
frontier.egg-info/PKG-INFO
frontier.egg-info/SOURCES.txt
frontier.egg-info/dependency_links.txt
frontier.egg-info/requires.txt
frontier.egg-info/top_level.txt
frontier/IO/AQCReader.py
frontier/IO/AbstractReader.py
frontier/IO/BamcheckReader.py
frontier/IO/__init__.py
tests/__init__.py
tests/test_aqcreader.py
tests/test_bamcheckreader.py
tests/test_frontier.py
tests/data/example.aqc.txt
tests/data/example.aqc.uniq.txt
tests/data/example.bamcheck.baddups.txt
tests/data/example.bamcheck.dups.txt
tests/data/example.bamcheck.txt