Metadata-Version: 1.1
Name: frontier
Version: 0.1.2
Summary: Provides interfaces for the reading, storage and retrieval of large machine learning data sets for use with scikit-learn
Home-page: https://github.com/samstudio8/frontier
Author: Sam Nicholls
Author-email: sam@samnicholls.net
License: UNKNOWN
Platform: UNKNOWN
Classifier: Development Status :: 2 - Pre-Alpha
Classifier: Intended Audience :: Developers
Classifier: Intended Audience :: Science/Research
Classifier: Programming Language :: Python :: 2
Classifier: Programming Language :: Python :: 2.7
Classifier: Programming Language :: Python :: 3
Classifier: Programming Language :: Python :: 3.3
Classifier: Topic :: Scientific/Engineering
Classifier: Topic :: Scientific/Engineering :: Bio-Informatics
